README.rst
setup.py
kcbo/__init__.py
kcbo/utils.py
kcbo.egg-info/PKG-INFO
kcbo.egg-info/SOURCES.txt
kcbo.egg-info/dependency_links.txt
kcbo.egg-info/requires.txt
kcbo.egg-info/top_level.txt
kcbo/statistical_tests/__init__.py
kcbo/statistical_tests/beta_binomial_difference.py
kcbo/statistical_tests/lognormal_comparison_test.py
kcbo/statistical_tests/pearson_correlation.py
kcbo/statistical_tests/t_test.py
kcbo/statistical_tests/utils.py