Metadata-Version: 1.1
Name: kcbo
Version: 0.0.1
Summary: Bayesian data analysis library
Home-page: https://github.com/HHammond/kcbo
Author: Henry Hammond
Author-email: henryhhammond92@gmail.com
License: MIT
Keywords: bayesian data analysis statistics
Platform: UNKNOWN
Classifier: Development Status :: 3 - Alpha
Classifier: License :: OSI Approved :: MIT License
Classifier: Programming Language :: Python
Classifier: Topic :: Scientific/Engineering
Classifier: Topic :: Scientific/Engineering :: Mathematics
